dxchange
wavepy
