Metadata-Version: 1.2
Name: wavepy
Version: 1.0.3
Summary: Wavepy kernel library
Home-page: https://github.com/aps-xsd-opt-group/wavepy
Author: Walan Grizolli
Author-email: wcgrizolli@anl.gov
Maintainer: XSD-OPT Group @ APS-ANL
Maintainer-email: lrebuffi@anl.gov
License: BSD-3
Download-URL: https://github.com/aps-xsd-opt-group/wavepy
Keywords: dictionary,glossary,synchrotronsimulation
Platform: UNKNOWN
Classifier: Development Status :: 4 - Beta
Classifier: License :: OSI Approved :: BSD License
Classifier: Natural Language :: English
Classifier: Environment :: Console
Classifier: Environment :: Plugins
Classifier: Programming Language :: Python :: 3.6
Classifier: Topic :: Scientific/Engineering :: Visualization
Classifier: Intended Audience :: Science/Research
